[
  {
    "name": "中华民国的成立",
    "p1": {
      "关系": "地点",
      "e1": "南京"
    },
    "p2": {
      "关系": "参与",
      "e1": "孙中山",
      "e2": "黄兴",
      "e3": "黎元洪"
    },
    "p3": {
      "关系": "背景",
      "e1": "辛亥革命"
    },
    "p4": {
      "关系": "影响",
      "e1": "颁布《中华民国临时约法》"
    }
  },
  {
    "name": "末代皇帝溥仪退位",
    "p1": {
      "关系": "地点",
      "e1": "北京"
    },
    "p2": {
      "关系": "参与",
      "e1": "爱新觉罗·溥仪",
      "e2": "袁世凯"
    },
    "p3": {
      "关系": "背景",
      "e1": "辛亥革命"
    },
    "p4": {
      "关系": "影响",
      "e1": "中华民国成立"
    }
  },
  {
    "name": "二次革命",
    "p1": {
      "关系": "时间",
      "e1": "1913年7月至9月"
    },
    "p2": {
      "关系": "地点",
      "e1": "江西、江苏、安徽、上海等地"
    },
    "p3": {
      "关系": "参与",
      "e1": "国民党",
      "e2": "袁世凯政府军"
    },
    "p4": {
      "关系": "背景",
      "e1": "袁世凯当选中华民国临时大总统",
      "e2": "宋教仁遇刺"
    },
    "p5": {
      "关系": "影响",
      "e1": "中华革命党在日本成立"
    }
  },
  {
    "name": "宋教仁遇刺",
    "p1": {
      "关系": "时间",
      "e1": "1913年3月20日晚10时45分"
    },
    "p2": {
      "关系": "地点",
      "e1": "上海北站"
    },
    "p3": {
      "关系": "参与",
      "e1": "宋教仁",
      "e2": "袁世凯"
    },
    "p4": {
      "关系": "背景",
      "e1": "袁世凯当选中华民国临时大总统",
      "e2": "北洋政府成立"
    },
    "p5": {
      "关系": "影响",
      "e1": "二次革命"
    }
  },
  {
    "name": "第一次世界大战爆发",
    "p1": {
      "关系": "地点",
      "e1": "欧洲"
    },
    "p2": {
      "关系": "参与",
      "e1": "奥匈帝国",
      "e2": "塞尔维亚",
      "e3": "德国"
    }
  },
  {
    "name": "中华革命党在日本成立",
    "p1": {
      "关系": "地点",
      "e1": "日本"
    },
    "p2": {
      "关系": "参与",
      "e1": "孙中山",
      "e2": "黄兴"
    },
    "p3": {
      "关系": "背景",
      "e1": "袁世凯复辟帝制",
      "e2": "二次革命"
    }
  },
  {
    "name": "新文化运动",
    "p1": {
      "关系": "参与",
      "e1": "胡适",
      "e2": "陈独秀",
      "e3": "鲁迅",
      "e4": "钱玄同",
      "e5": "李大钊"
    },
    "p2": {
      "关系": "背景",
      "e1": "第一次世界大战",
      "e2": "俄国十月革命"
    },
    "p3": {
      "关系": "影响",
      "e1": "五四运动",
      "e2": "中国共产党的成立"
    }
  },
  {
    "name": "护国运动",
    "p1": {
      "关系": "地点",
      "e1": "西南地区"
    },
    "p2": {
      "关系": "参与",
      "e1": "唐继尧",
      "e2": "蔡锷",
      "e3": "李烈钧"
    },
    "p3": {
      "关系": "背景",
      "e1": "袁世凯复辟帝制"
    },
    "p4": {
      "关系": "影响",
      "e1": "袁世凯取消帝制"
    }
  },
  {
    "name": "袁世凯宣布取消帝制",
    "p1": {
      "关系": "地点",
      "e1": "北京"
    },
    "p2": {
      "关系": "参与",
      "e1": "袁世凯"
    },
    "p3": {
      "关系": "背景",
      "e1": "袁世凯复辟帝制",
      "e2": "护国运动"
    }
  },
  {
    "name": "辛亥革命党人陈其美遇刺身亡",
    "p1": {
      "关系": "地点",
      "e1": "上海法租界萨坡赛路14号寓所"
    },
    "p2": {
      "关系": "参与",
      "e1": "陈其美",
      "e2": "张宗昌",
      "e3": "袁世凯"
    },
    "p3": {
      "关系": "背景",
      "e1": "辛亥革命"
    }
  },
  {
    "name": "护法运动",
    "p1": {
      "关系": "地点",
      "e1": "广州"
    },
    "p2": {
      "关系": "参与",
      "e1": "孙中山",
      "e2": "唐继尧",
      "e3": "陆荣廷"
    },
    "p3": {
      "关系": "背景",
      "e1": "段祺瑞废除《中华民国临时约法》"
    },
    "p4": {
      "关系": "影响",
      "e1": "北伐战争",
      "e2": "新文化运动"
    }
  },
  {
    "name": "张勋复辟",
    "p1": {
      "关系": "地点",
      "e1": "北京"
    },
    "p2": {
      "关系": "参与",
      "e1": "张勋",
      "e2": "康有为",
      "e3": "黎元洪",
      "e4": "段祺瑞"
    },
    "p3": {
      "关系": "影响",
      "e1": "北伐战争",
      "e2": "新文化运动"
    }
  },
  {
    "name": "新国会成立",
    "p1": {
      "关系": "地点",
      "e1": "北京"
    },
    "p2": {
      "关系": "参与",
      "e1": "李兆珍",
      "e2": "冯国璋",
      "e3": "段祺瑞"
    },
    "p3": {
      "关系": "背景",
      "e1": "旧国会的解散"
    }
  },
  {
    "name": "《狂人日记》著成",
    "p1": {
      "关系": "地点",
      "e1": "绍兴会馆"
    },
    "p2": {
      "关系": "参与",
      "e1": "鲁迅",
      "e2": "钱玄同（编辑邀请鲁迅创作）"
    },
    "p3": {
      "关系": "背景",
      "e1": "俄国十月革命胜利",
      "e2": "新文化运动"
    }
  },
  {
    "name": "五四运动",
    "p1": {
      "关系": "地点",
      "e1": "北京"
    },
    "p2": {
      "关系": "参与",
      "e1": "北京大学学生",
      "e2": "高等师范学校学生",
      "e3": "北京其他高校学生",
      "e4": "市民",
      "e5": "工商人士"
    },
    "p3": {
      "关系": "背景",
      "e1": "第一次世界大战结束",
      "e2": "中国在巴黎和会上的外交失败",
      "e3": "新文化运动"
    },
    "p4": {
      "关系": "影响",
      "e1": "促进了中国人民的觉醒和爱国热情",
      "e2": "新文化运动",
      "e3": "中国共产党的成立",
      "e4": "标志着中国民主革命进入了一个新阶段"
    }
  },
  {
    "name": "巴黎和会",
    "p1": {
      "关系": "地点",
      "e1": "法国巴黎凡尔赛宫"
    },
    "p2": {
      "关系": "参与",
      "e1": "伍德罗·威尔逊（美国总统）",
      "e2": "劳合·乔治（英国首相）",
      "e3": "克里孟梭（法国总理）",
      "e4": "维托里奥·埃马努埃莱三世（意大利国王代表）",
      "e5": "陆宗祥（中国代表团成员）",
      "e6": "顾维钧（中国代表团成员）"
    },
    "p3": {
      "关系": "背景",
      "e1": "第一次世界大战结束"
    },
    "p4": {
      "关系": "影响",
      "e1": "国际联盟成立",
      "e2": "新民主主义革命的兴起",
      "e3": "五四运动"
    }
  },
  {
    "name": "国际联盟成立",
    "p1": {
      "关系": "地点",
      "e1": "瑞士日内瓦"
    },
    "p2": {
      "关系": "参与",
      "e1": "伍德罗·威尔逊（美国总统）",
      "e2": "劳合·乔治（英国首相）",
      "e3": "克里孟梭（法国总理）"
    },
    "p3": {
      "关系": "背景",
      "e1": "第一次世界大战结束",
      "e2": "巴黎和会的召开"
    }
  },
  {
    "name": "直皖战争",
    "p1": {
      "关系": "地点",
      "e1": "中国北方，特别是北京周边地区"
    },
    "p2": {
      "关系": "参与",
      "e1": "吴佩孚",
      "e2": "段祺瑞",
      "e3": "张作霖"
    },
    "p3": {
      "关系": "影响",
      "e1": "北伐战争"
    }
  },
  {
    "name": "中国劳动组合书记部成立",
    "p1": {
      "关系": "地点",
      "e1": "上海"
    },
    "p2": {
      "关系": "参与",
      "e1": "张国焘",
      "e2": "邓中夏",
      "e3": "李启汉"
    },
    "p3": {
      "关系": "背景",
      "e1": "中国共产党成立",
      "e2": "借鉴俄国布尔什维克党领导工人运动的经验"
    }
  },
  {
    "name": "中国共产党成立",
    "p1": {
      "关系": "地点",
      "e1": "上海法租界望志路106号（现兴业路76号）和浙江嘉兴"
    },
    "p2": {
      "关系": "参与",
      "e1": "李达",
      "e2": "李汉俊",
      "e3": "张国焘",
      "e4": "刘仁静",
      "e5": "毛泽东",
      "e6": "何叔衡",
      "e7": "董必武",
      "e8": "陈潭秋",
      "e9": "王尽美",
      "e10": "邓恩铭",
      "e11": "陈公博",
      "e12": "包惠僧",
      "e13": "周佛海"
    },
    "p3": {
      "关系": "背景",
      "e1": "十月革命",
      "e2": "五四运动"
    },
    "p4": {
      "关系": "影响",
      "e1": "中华苏维埃共和国的建立"
    }
  },
  {
    "name": "中国共产党第二次全国代表大会",
    "p1": {
      "关系": "地点",
      "e1": "上海南成都路辅德里625号"
    },
    "p2": {
      "关系": "参与",
      "e1": "陈独秀",
      "e2": "张国焘",
      "e3": "李达",
      "e4": "蔡和森",
      "e5": "李汉俊",
      "e6": "邓中夏",
      "e7": "谭平山",
      "e8": "向警予",
      "e9": "项英",
      "e10": "罗章龙",
      "e11": "蔡畅",
      "e12": "高君宇",
      "e13": "施存统"
    }
  },
  {
    "name": "安源路矿工人罢工",
    "p1": {
      "关系": "地点",
      "e1": "江西安源"
    },
    "p2": {
      "关系": "参与",
      "e1": "李立三",
      "e2": "刘少奇"
    },
    "p3": {
      "关系": "影响",
      "e1": "京汉铁路工人总罢工"
    }
  },
  {
    "name": "中共三大",
    "p1": {
      "关系": "地点",
      "e1": "广州"
    },
    "p2": {
      "关系": "参与",
      "e1": "陈独秀",
      "e2": "李大钊",
      "e3": "毛泽东",
      "e4": "蔡和森",
      "e5": "陈潭秋",
      "e6": "恽代英",
      "e7": "瞿秋白",
      "e8": "张国焘",
      "e9": "李立三",
      "e10": "项英"
    },
    "p3": {
      "关系": "背景",
      "e1": "北洋政府的统治"
    },
    "p4": {
      "关系": "影响",
      "e1": "第一次国共合作"
    }
  },
  {
    "name": "京汉铁路工人总罢工",
    "p1": {
      "关系": "地点",
      "e1": "京汉铁路沿线"
    },
    "p2": {
      "关系": "参与",
      "e1": "林祥谦",
      "e2": "施洋"
    },
    "p3": {
      "关系": "背景",
      "e1": "中国共产党的发展"
    }
  },
  {
    "name": "国共第一次合作",
    "p1": {
      "关系": "参与",
      "e1": "孙中山",
      "e2": "李大钊",
      "e3": "毛泽东"
    },
    "p2": {
      "关系": "背景",
      "e1": "五四运动",
      "e2": "工人运动的发展",
      "e3": "北洋政府的统治"
    },
    "p3": {
      "关系": "影响",
      "e1": "北伐战争",
      "e2": "工农运动的高涨"
    }
  },
  {
    "name": "黄埔军校成立",
    "p1": {
      "关系": "地点",
      "e1": "广州"
    },
    "p2": {
      "关系": "参与",
      "e1": "孙中山",
      "e2": "蒋介石",
      "e3": "廖仲恺",
      "e4": "周恩来"
    },
    "p3": {
      "关系": "背景",
      "e1": "第一次国共合作的形成",
      "e2": "北洋军阀的统治"
    },
    "p4": {
      "关系": "影响",
      "e1": "北伐战争",
      "e2": "抗日战争"
    }
  },
  {
    "name": "五卅惨案",
    "p1": {
      "关系": "地点",
      "e1": "上海"
    },
    "p2": {
      "关系": "背景",
      "e1": "上海罢工"
    }
  },
  {
    "name": "省港大罢工",
    "p1": {
      "关系": "地点",
      "e1": "广州、香港"
    },
    "p2": {
      "关系": "参与",
      "e1": "邓中夏",
      "e2": "苏兆征"
    },
    "p3": {
      "关系": "背景",
      "e1": "五卅惨案",
      "e2": "国共合作"
    }
  },
  {
    "name": "上海工人三次武装起义",
    "p1": {
      "关系": "地点",
      "e1": "上海"
    },
    "p2": {
      "关系": "参与",
      "e1": "上海工人纠察队",
      "e2": "上海总工会",
      "e3": "周恩来",
      "e4": "赵世炎",
      "e5": "罗亦农",
      "e6": "汪寿华"
    },
    "p3": {
      "关系": "背景",
      "e1": "北伐战争",
      "e2": "上海罢工"
    }
  },
  {
    "name": "北伐战争的爆发",
    "p1": {
      "关系": "地点",
      "e1": "中国南方"
    },
    "p2": {
      "关系": "参与",
      "e1": "国民革命军",
      "e2": "蒋介石",
      "e3": "李宗仁",
      "e4": "白崇禧",
      "e5": "李济深"
    },
    "p3": {
      "关系": "背景",
      "e1": "国共第一次合作",
      "e2": "北洋军阀内部的分裂"
    },
    "p4": {
      "关系": "影响",
      "e1": "北洋军阀的覆灭",
      "e2": "抗日战争"
    }
  },
  {
    "name": "南昌起义",
    "p1": {
      "关系": "地点",
      "e1": "江西南昌"
    },
    "p2": {
      "关系": "参与",
      "e1": "周恩来",
      "e2": "贺龙",
      "e3": "李立三",
      "e4": "叶挺",
      "e5": "朱德",
      "e6": "刘伯承",
      "e7": "谭平山"
    },
    "p3": {
      "关系": "背景",
      "e1": "国共合作破裂"
    },
    "p4": {
      "关系": "影响",
      "e1": "工农红军的建立",
      "e2": "抗日战争"
    }
  },
  {
    "name": "四一二政变",
    "p1": {
      "关系": "地点",
      "e1": "中国上海"
    },
    "p2": {
      "关系": "参与",
      "e1": "蒋介石",
      "e2": "白崇禧",
      "e3": "汪精卫"
    },
    "p3": {
      "关系": "背景",
      "e1": "国共合作破裂"
    },
    "p4": {
      "关系": "影响",
      "e1": "大革命失败",
      "e2": "国共合作破裂",
      "e3": "南昌起义"
    }
  },
  {
    "name": "北伐战争胜利",
    "p1": {
      "关系": "地点",
      "e1": "中国北方"
    },
    "p2": {
      "关系": "参与",
      "e1": "国民革命军",
      "e2": "蒋介石",
      "e3": "李宗仁",
      "e4": "白崇禧",
      "e5": "何应钦",
      "e6": "冯玉祥"
    },
    "p3": {
      "关系": "背景",
      "e1": "国共第一次合作",
      "e2": "五卅运动"
    },
    "p4": {
      "关系": "影响",
      "e1": "北洋军阀的推翻"
    }
  },
  {
    "name": "张作霖之死",
    "p1": {
      "关系": "地点",
      "e1": "皇姑屯"
    },
    "p2": {
      "关系": "参与",
      "e1": "张作霖",
      "e2": "日本关东军"
    },
    "p3": {
      "关系": "影响",
      "e1": "张学良接任东北军",
      "e2": "九一八事变"
    }
  },
  {
    "name": "蒋桂战争爆发",
    "p1": {
      "关系": "地点",
      "e1": "中国境内"
    },
    "p2": {
      "关系": "参与",
      "e1": "蒋介石",
      "e2": "李宗仁",
      "e3": "白崇禧"
    }
  },
  {
    "name": "中东路事件爆发",
    "p1": {
      "关系": "地点",
      "e1": "中苏边境"
    },
    "p2": {
      "关系": "参与",
      "e1": "张学良",
      "e2": "东北军",
      "e3": "苏联红军"
    },
    "p3": {
      "关系": "背景",
      "e1": "中东铁路的管理权争议"
    }
  },
  {
    "name": "中原大战",
    "p1": {
      "关系": "地点",
      "e1": "中原地区"
    },
    "p2": {
      "关系": "参与",
      "e1": "蒋介石",
      "e2": "冯玉祥",
      "e3": "阎锡山",
      "e4": "李宗仁",
      "e5": "张学良"
    },
    "p3": {
      "关系": "背景",
      "e1": "张学良东北军入关"
    }
  },
  {
    "name": "第一次围剿",
    "p1": {
      "关系": "地点",
      "e1": "中央苏区"
    },
    "p2": {
      "关系": "参与",
      "e1": "毛泽东",
      "e2": "朱德",
      "e3": "彭德怀",
      "e4": "蒋介石"
    },
    "p3": {
      "关系": "影响",
      "e1": "巩固了中央苏区",
      "e2": "反“围剿”斗争"
    }
  },
  {
    "name": "抗日战争爆发",
    "p1": {
      "关系": "地点",
      "e1": "中国全境，包括正面战场和敌后战场"
    },
    "p2": {
      "关系": "参与",
      "e1": "中国军队与民众",
      "e2": "日本军队",
      "e3": "国民党军队",
      "e4": "八路军",
      "e5": "新四军",
      "e6": "抗日根据地民众"
    },
    "p3": {
      "关系": "背景",
      "e1": "九一八事变"
    },
    "p4": {
      "关系": "影响",
      "e1": "中国人民抗日战争胜利",
      "e2": "世界反法西斯战争胜利"
    }
  },
  {
    "name": "九一八事变",
    "p1": {
      "关系": "地点",
      "e1": "沈阳"
    },
    "p2": {
      "关系": "参与",
      "e1": "日本关东军",
      "e2": "东北军",
      "e3": "本庄繁",
      "e4": "张学良"
    },
    "p3": {
      "关系": "背景",
      "e1": "国民政府的不抵抗政策"
    },
    "p4": {
      "关系": "影响",
      "e1":  "抗日民族统一战线的建立",
      "e2": "东北抗日义勇军"
    }
  }
]